autogenerated_api/__init__.py
autogenerated_api/autogenerated_urls.py
autogenerated_api/autogeneration.py
autogenerated_api/model_tools.py
autogenerated_api/serializers.py
autogenerated_api/tools.py
autogenerated_api-1.2.6.dist-info/LICENSE
autogenerated_api-1.2.6.dist-info/METADATA
autogenerated_api-1.2.6.dist-info/WHEEL
autogenerated_api-1.2.6.dist-info/top_level.txt
autogenerated_api-1.2.6.dist-info/RECORD
